classwerk/__init__.py
classwerk/cli.py
classwerk/utils.py
classwerk/cmds/__init__.py
classwerk/cmds/delete_repos.py
classwerk/cmds/download_submissions.py
classwerk/cmds/init_repos.py
classwerk/cmds/push_files.py
classwerk/cmds/tag_submissions.py
classwerk/orig/__init__.py
classwerk/orig/collect_results.py
classwerk/orig/create_repos.py
classwerk/orig/create_teams.py
classwerk/orig/delete_repos.py
classwerk/orig/download_submissions.py
classwerk/orig/push_files.py
classwerk/orig/tag_submissions.py
classwerk-0.0.2.dist-info/DESCRIPTION.rst
classwerk-0.0.2.dist-info/entry_points.txt
classwerk-0.0.2.dist-info/METADATA
classwerk-0.0.2.dist-info/metadata.json
classwerk-0.0.2.dist-info/pbr.json
classwerk-0.0.2.dist-info/RECORD
classwerk-0.0.2.dist-info/top_level.txt
classwerk-0.0.2.dist-info/WHEEL
